MANIFEST.in
README.rst
hkdf.py
setup.py
hkdf.egg-info/PKG-INFO
hkdf.egg-info/SOURCES.txt
hkdf.egg-info/dependency_links.txt
hkdf.egg-info/top_level.txt